opentau/__init__.py
opentau/__version__.py
opentau/constants.py
opentau/configs/__init__.py
opentau/configs/default.py
opentau/configs/libero.py
opentau/configs/parser.py
opentau/configs/policies.py
opentau/configs/reward.py
opentau/configs/train.py
opentau/configs/types.py
opentau/datasets/__init__.py
opentau/datasets/backward_compatibility.py
opentau/datasets/compute_stats.py
opentau/datasets/dataset_mixture.py
opentau/datasets/factory.py
opentau/datasets/image_writer.py
opentau/datasets/lerobot_dataset.py
opentau/datasets/online_buffer.py
opentau/datasets/sampler.py
opentau/datasets/standard_data_format_mapping.py
opentau/datasets/transforms.py
opentau/datasets/utils.py
opentau/datasets/video_utils.py
opentau/datasets/grounding/__init__.py
opentau/datasets/grounding/base.py
opentau/datasets/grounding/clevr.py
opentau/datasets/grounding/cocoqa.py
opentau/datasets/grounding/dummy.py
opentau/datasets/grounding/pixmo.py
opentau/datasets/grounding/vsr.py
opentau/datasets/push_dataset_to_hub/utils.py
opentau/datasets/v2/batch_convert_dataset_v1_to_v2.py
opentau/datasets/v2/convert_dataset_v1_to_v2.py
opentau/datasets/v21/_remove_language_instruction.py
opentau/datasets/v21/batch_convert_dataset_v20_to_v21.py
opentau/datasets/v21/convert_dataset_v20_to_v21.py
opentau/datasets/v21/convert_stats.py
opentau/envs/__init__.py
opentau/envs/configs.py
opentau/envs/factory.py
opentau/envs/libero.py
opentau/envs/utils.py
opentau/optim/__init__.py
opentau/optim/factory.py
opentau/optim/optimizers.py
opentau/optim/schedulers.py
opentau/planner/__init__.py
opentau/planner/high_level_planner.py
opentau/planner/utils/memory.py
opentau/planner/utils/utils.py
opentau/policies/__init__.py
opentau/policies/factory.py
opentau/policies/normalize.py
opentau/policies/pretrained.py
opentau/policies/utils.py
opentau/policies/pi0/__init__.py
opentau/policies/pi0/configuration_pi0.py
opentau/policies/pi0/modeling_pi0.py
opentau/policies/pi0/paligemma_with_expert.py
opentau-0.1.2.dist-info/licenses/LICENSE
opentau-0.1.2.dist-info/METADATA
opentau-0.1.2.dist-info/WHEEL
opentau-0.1.2.dist-info/entry_points.txt
opentau-0.1.2.dist-info/top_level.txt
opentau-0.1.2.dist-info/RECORD
